LICENSE
MANIFEST.in
README.md
dev_requirements.txt
prod_requirements.txt
setup.cfg
setup.py
version.txt
shekels/__init__.py
shekels.egg-info/PKG-INFO
shekels.egg-info/SOURCES.txt
shekels.egg-info/dependency_links.txt
shekels.egg-info/requires.txt
shekels.egg-info/top_level.txt
shekels/core/__init__.py
shekels/core/config.py
shekels/core/data_tools.py
shekels/core/database.py
shekels/enforce/__init__.py
shekels/enforce/enforce_tools.py
shekels/resources/icon.svg
shekels/resources/test_config.json
shekels/resources/test_transactions.csv
shekels/server/__init__.py
shekels/server/api.py
shekels/server/app.py
shekels/server/components.py
shekels/server/event_listener.py
shekels/server/server_tools.py
shekels/templates/style.css.j2