Metadata-Version: 2.1
Name: shekels
Version: 1.0.3
Summary: Shekels is a local service which consumes a transactions CSV file downloaded from mint.intuit.com. It conforms this data into a database, and displays it as a searchable table and dashboard of configurable plots in web frontend.
Home-page: https://github.com/theNewFlesh/shekels
Author: Alex Braun
Author-email: Alexander.G.Braun@gmail.com
License: MIT
Download-URL: https://github.com/theNewFlesh/shekels/archive/1.0.3.tar.gz
Keywords: dashboard,data,database,datastore,finance,flask,json,plotly,service
Platform: UNKNOWN
Classifier: Development Status :: 4 - Beta
Classifier: Intended Audience :: Developers
Classifier: License :: OSI Approved :: MIT License
Classifier: Programming Language :: Python :: 3
Classifier: Programming Language :: Python :: 3.7
Provides-Extra: dev
License-File: LICENSE
